mssql/__init__.py
mssql/dbmanager.py
mssql/ephemeralmssqldbcontext.py
mssql/ephemeralmssqldbcontextbuilder.py
mssql/filesmanager.py
ephemerals_mssql-1.0.5.dist-info/LICENSE.md
ephemerals_mssql-1.0.5.dist-info/METADATA
ephemerals_mssql-1.0.5.dist-info/WHEEL
ephemerals_mssql-1.0.5.dist-info/top_level.txt
ephemerals_mssql-1.0.5.dist-info/RECORD
